{
    "hbrimd": {
        "author_fullname": "t2_6xmzg79e",
        "author_name": "Helpful__Alfalfa",
        "created_utc": 1592530504.0,
        "domain": "biography.com",
        "gilded": 1,
        "gildings": {},
        "id": "hbrimd",
        "is_created_from_ads_ui": false,
        "is_original_content": false,
        "is_reddit_media_domain": false,
        "is_self": false,
        "is_video": false,
        "link_flair_text": "",
        "media_only": false,
        "num_comments": 1847,
        "over_18": false,
        "permalink": "/r/todayilearned/comments/hbrimd/til_during_an_interview_with_stephen_hawking_the/",
        "score": 167288,
        "subreddit": "todayilearned",
        "subreddit_id": "2qqjc",
        "text": null,
        "title": "TIL During an interview with Stephen Hawking, the camera operator yanked a cable causing an alarm and Hawking to slump forward. Worried they had killed him, everyone rushed over to find Hawking giggling at his own joke. The alarm was from an office computer losing power.",
        "total_awards_received": 0,
        "upvote_ratio": 0.97,
        "url": "https://www.biography.com/news/stephen-hawking-zingers"
    },
    "lgl7ag": {
        "author_fullname": "t2_4j1a4ajn",
        "author_name": "_pancake_lover_",
        "created_utc": 1612928848.0,
        "domain": "thetyee.ca",
        "gilded": 1,
        "gildings": {},
        "id": "lgl7ag",
        "is_created_from_ads_ui": false,
        "is_original_content": false,
        "is_reddit_media_domain": false,
        "is_self": false,
        "is_video": false,
        "link_flair_text": "",
        "media_only": false,
        "num_comments": 3313,
        "over_18": false,
        "permalink": "/r/todayilearned/comments/lgl7ag/til_genghis_khan_would_marry_off_a_daughter_to/",
        "score": 165477,
        "subreddit": "todayilearned",
        "subreddit_id": "2qqjc",
        "text": null,
        "title": "TIL Genghis Khan would marry off a daughter to the king of an allied nation. Then he would assign his new son in law to military duty in the Mongol wars, while his daughter took over the rule. Most sons in law died in combat, giving his daughters complete control of these nations",
        "total_awards_received": 0,
        "upvote_ratio": 0.95,
        "url": "https://thetyee.ca/Books/2010/07/26/GenghisFeminist/"
    },
    "gjmajm": {
        "author_fullname": "t2_v51f9",
        "author_name": "Miskatonica",
        "created_utc": 1589462742.0,
        "domain": "nydailynews.com",
        "gilded": 1,
        "gildings": {},
        "id": "gjmajm",
        "is_created_from_ads_ui": false,
        "is_original_content": false,
        "is_reddit_media_domain": false,
        "is_self": false,
        "is_video": false,
        "link_flair_text": "",
        "media_only": false,
        "num_comments": 7822,
        "over_18": false,
        "permalink": "/r/todayilearned/comments/gjmajm/til_the_fbi_has_struggled_to_hire_hackers_because/",
        "score": 159884,
        "subreddit": "todayilearned",
        "subreddit_id": "2qqjc",
        "text": null,
        "title": "TIL the FBI has struggled to hire hackers because of the FBI hiring rule that the applicant must not have used marijuana during the last 3 years.",
        "total_awards_received": 0,
        "upvote_ratio": 0.96,
        "url": "https://www.nydailynews.com/life-style/fbi-struggling-find-good-hackers-due-pot-rules-article-1.3949920"
    },
    "8ih4tq": {
        "author_fullname": "t2_nyx3x",
        "author_name": "bpbucko614",
        "created_utc": 1525977258.0,
        "domain": "huffingtonpost.com",
        "gilded": 1,
        "gildings": {},
        "id": "8ih4tq",
        "is_created_from_ads_ui": false,
        "is_original_content": false,
        "is_reddit_media_domain": false,
        "is_self": false,
        "is_video": false,
        "link_flair_text": "",
        "media_only": false,
        "num_comments": 5402,
        "over_18": false,
        "permalink": "/r/todayilearned/comments/8ih4tq/til_that_in_1916_there_was_a_proposed_amendment/",
        "score": 159419,
        "subreddit": "todayilearned",
        "subreddit_id": "2qqjc",
        "text": null,
        "title": "TIL that in 1916 there was a proposed Amendment to the US Constitution that would put all acts of war to a national vote, and anyone voting yes would have to register as a volunteer for service in the United States Army.",
        "total_awards_received": 0,
        "upvote_ratio": 0.94,
        "url": "https://www.huffingtonpost.com/2013/09/04/amendment-war-national-vote_n_3866686.html"
    },
    "7pbzcb": {
        "author_fullname": "t2_3tgsy",
        "author_name": "Tartantyco",
        "created_utc": 1515546833.0,
        "domain": "en.wikipedia.org",
        "gilded": 4,
        "gildings": {},
        "id": "7pbzcb",
        "is_created_from_ads_ui": false,
        "is_original_content": false,
        "is_reddit_media_domain": false,
        "is_self": false,
        "is_video": false,
        "link_flair_text": "",
        "media_only": false,
        "num_comments": 4225,
        "over_18": false,
        "permalink": "/r/todayilearned/comments/7pbzcb/til_after_col_shaw_died_in_battle_confederates/",
        "score": 158633,
        "subreddit": "todayilearned",
        "subreddit_id": "2qqjc",
        "text": null,
        "title": "TIL After Col. Shaw died in battle, Confederates buried him in a mass grave as an insult for leading black soldiers. Union troops tried to recover his body, but his father sent a letter saying \"We would not have his body removed from where it lies surrounded by his brave and devoted soldiers.\"",
        "total_awards_received": 0,
        "upvote_ratio": 0.93,
        "url": "https://en.wikipedia.org/wiki/Robert_Gould_Shaw#Death_at_the_Second_Battle_of_Fort_Wagner"
    },
    "i8pq5h": {
        "author_fullname": "t2_66l6u5c9",
        "author_name": "RarelyAquatic",
        "created_utc": 1597278293.0,
        "domain": "revolt.tv",
        "gilded": 1,
        "gildings": {},
        "id": "i8pq5h",
        "is_created_from_ads_ui": false,
        "is_original_content": false,
        "is_reddit_media_domain": false,
        "is_self": false,
        "is_video": false,
        "link_flair_text": "",
        "media_only": false,
        "num_comments": 3147,
        "over_18": false,
        "permalink": "/r/todayilearned/comments/i8pq5h/til_a_fan_drove_three_hours_to_deliver_rapper/",
        "score": 157758,
        "subreddit": "todayilearned",
        "subreddit_id": "2qqjc",
        "text": null,
        "title": "TIL a fan drove three hours to deliver rapper, Boozie Badazz, a much needed dosage of insulin. She refused to accept payment and instead asked for just a photo. On her way home she stopped at a store, bought a scratch off ticket, and won $10,000.",
        "total_awards_received": 0,
        "upvote_ratio": 0.94,
        "url": "https://www.revolt.tv/platform/amp/news/2020/4/27/21239043/boosie-badazz-insulin-scratch-off"
    },
    "tlmlnw": {
        "author_fullname": "t2_46mjlg2g",
        "author_name": "the_freshest_scone",
        "created_utc": 1648079645.0,
        "domain": "looper.com",
        "gilded": 1,
        "gildings": {},
        "id": "tlmlnw",
        "is_created_from_ads_ui": false,
        "is_original_content": false,
        "is_reddit_media_domain": false,
        "is_self": false,
        "is_video": false,
        "link_flair_text": "",
        "media_only": false,
        "num_comments": 3614,
        "over_18": false,
        "permalink": "/r/todayilearned/comments/tlmlnw/til_that_the_animal_planet_reality_series_river/",
        "score": 155347,
        "subreddit": "todayilearned",
        "subreddit_id": "2qqjc",
        "text": null,
        "title": "TIL that the Animal Planet reality series \u2018River Monsters\u2019 ended because star Jeremy Wade was able to catch essentially every exceptionally large freshwater fish species on earth, leaving no remaining content for the show",
        "total_awards_received": 0,
        "upvote_ratio": 0.96,
        "url": "https://www.looper.com/72292/untold-truth-river-monsters/"
    },
    "eb15tp": {
        "author_fullname": "t2_a5mp9",
        "author_name": "Eric__Fapton",
        "created_utc": 1576428431.0,
        "domain": "today.com",
        "gilded": 2,
        "gildings": {},
        "id": "eb15tp",
        "is_created_from_ads_ui": false,
        "is_original_content": false,
        "is_reddit_media_domain": false,
        "is_self": false,
        "is_video": false,
        "link_flair_text": "",
        "media_only": false,
        "num_comments": 2756,
        "over_18": false,
        "permalink": "/r/todayilearned/comments/eb15tp/til_actor_robert_pattinson_dealt_with_an_obsessed/",
        "score": 151700,
        "subreddit": "todayilearned",
        "subreddit_id": "2qqjc",
        "text": null,
        "title": "TIL actor Robert Pattinson dealt with an obsessed fan who had been camping outside his apartment by taking her out on a dinner date. \"I just complained about everything in my life and she never came back.\"",
        "total_awards_received": 0,
        "upvote_ratio": 0.96,
        "url": "https://www.today.com/popculture/twilight-star-says-he-bores-people-2-minutes-wbna29123100"
    },
    "ejwxed": {
        "author_fullname": "t2_51xzw252",
        "author_name": "meowroarhiss",
        "created_utc": 1578146348.0,
        "domain": "mother.ly",
        "gilded": 1,
        "gildings": {},
        "id": "ejwxed",
        "is_created_from_ads_ui": false,
        "is_original_content": false,
        "is_reddit_media_domain": false,
        "is_self": false,
        "is_video": false,
        "link_flair_text": "",
        "media_only": false,
        "num_comments": 6993,
        "over_18": false,
        "permalink": "/r/todayilearned/comments/ejwxed/til_that_millennial_dads_are_spending_3_times_as/",
        "score": 150133,
        "subreddit": "todayilearned",
        "subreddit_id": "2qqjc",
        "text": null,
        "title": "TIL that millennial dads are spending 3 times as much times with their kids than their fathers spent with them. Back in 1982, 43% of fathers admitted they'd never changed a diaper. Today, that number is down to about 3%.",
        "total_awards_received": 0,
        "upvote_ratio": 0.95,
        "url": "https://www.mother.ly/news/millennial-dads-spend-more-time-with-their-kids?rebelltitem=1#rebelltitem1"
    },
    "i7irad": {
        "author_fullname": "t2_4b48x",
        "author_name": "imsiq",
        "created_utc": 1597110829.0,
        "domain": "cheatsheet.com",
        "gilded": 0,
        "gildings": {},
        "id": "i7irad",
        "is_created_from_ads_ui": false,
        "is_original_content": false,
        "is_reddit_media_domain": false,
        "is_self": false,
        "is_video": false,
        "link_flair_text": "",
        "media_only": false,
        "num_comments": 5490,
        "over_18": false,
        "permalink": "/r/todayilearned/comments/i7irad/til_the_cast_of_friends_each_made_1m_per_episode/",
        "score": 149054,
        "subreddit": "todayilearned",
        "subreddit_id": "2qqjc",
        "text": null,
        "title": "TIL The cast of FRIENDS each made $1M per episode in the final two seasons and now make $20M per year per cast member for reruns. The show still generates $1B/year for Warner Bros. All thanks to David Schwimmer encouraging the cast to negotiate as a team.",
        "total_awards_received": 0,
        "upvote_ratio": 0.94,
        "url": "https://www.cheatsheet.com/entertainment/how-much-money-does-the-cast-of-friends-make-for-reruns.html/"
    }
}